odoo/addons/purchase_mrp_distribution/README.rst
odoo/addons/purchase_mrp_distribution/__init__.py
odoo/addons/purchase_mrp_distribution/__manifest__.py
odoo/addons/purchase_mrp_distribution/i18n/es.po
odoo/addons/purchase_mrp_distribution/i18n/it.po
odoo/addons/purchase_mrp_distribution/i18n/purchase_mrp_distribution.pot
odoo/addons/purchase_mrp_distribution/models/__init__.py
odoo/addons/purchase_mrp_distribution/models/mrp_bom.py
odoo/addons/purchase_mrp_distribution/models/purchase.py
odoo/addons/purchase_mrp_distribution/models/stock_move.py
odoo/addons/purchase_mrp_distribution/readme/CONFIGURE.md
odoo/addons/purchase_mrp_distribution/readme/CONTEXT.md
odoo/addons/purchase_mrp_distribution/readme/CONTRIBUTORS.md
odoo/addons/purchase_mrp_distribution/readme/DESCRIPTION.md
odoo/addons/purchase_mrp_distribution/readme/ROADMAP.md
odoo/addons/purchase_mrp_distribution/readme/USAGE.md
odoo/addons/purchase_mrp_distribution/security/ir.model.access.csv
odoo/addons/purchase_mrp_distribution/static/description/icon.png
odoo/addons/purchase_mrp_distribution/static/description/index.html
odoo/addons/purchase_mrp_distribution/tests/__init__.py
odoo/addons/purchase_mrp_distribution/tests/test_purchase_mrp_distribution.py
odoo/addons/purchase_mrp_distribution/views/mrp_bom_views.xml
odoo/addons/purchase_mrp_distribution/views/stock_picking_views.xml
odoo/addons/purchase_mrp_distribution/wizards/__init__.py
odoo/addons/purchase_mrp_distribution/wizards/stock_move_distribution_wiz.py
odoo/addons/purchase_mrp_distribution/wizards/stock_move_distribution_wiz_views.xml
odoo_addon_purchase_mrp_distribution-17.0.1.0.0.4.dist-info/METADATA
odoo_addon_purchase_mrp_distribution-17.0.1.0.0.4.dist-info/WHEEL
odoo_addon_purchase_mrp_distribution-17.0.1.0.0.4.dist-info/top_level.txt
odoo_addon_purchase_mrp_distribution-17.0.1.0.0.4.dist-info/RECORD
